	<PAGE_LCI>
		<FICHIER>lci-monde-2005-03-26.html</FICHIER>
		<DATE_PAGE>26/03/2005</DATE_PAGE>
		<UNE>
			<urlArticle>/news/monde/0,,3209565-VU5WX0lEIDUy,00.html</urlArticle>
			<titreArticle>L'&#195;&#169;tat du prince Rainier s'aggrave</titreArticle>
			<dateArticle>26/03/2005</dateArticle>
			<urlImage>http://s.tf1.fr/mmdia/i/20/4/609204.gif</urlImage>
			<resumeArticle> L'&#195;&#169;tat de sant&#195;&#169; du prince Rainier de Monaco "ne cesse de s'aggraver" et son pronostic vital est "extr&#195;&#170;mement r&#195;&#169;serv&#195;&#169;", a indiqu&#195;&#169; samedi midi le palais. Jean-Paul II a adress&#195;&#169; ce matin "une particuli&#195;&#168;re b&#195;&#169;n&#195;&#169;diction" au prince Rainier ainsi qu'&#195;&#160; ses proches. Jacques Chirac a t&#195;&#169;l&#195;&#169;phon&#195;&#169; au prince Albert pour lui dire "son amiti&#195;&#169; et sa sollicitude&#194;&#160;pour lui-m&#195;&#170;me, sa famille et le peuple mon&#195;&#169;gasque".</resumeArticle>
			<mailto></mailto>
		</UNE>
		<LES_VOIRAUSSI>
			<VOIRAUSSI>
				<dateArticle>25/03/2005</dateArticle>
				<urlArticle>/news/0,,3209703-VU5WX0lEIDUy,00.html</urlArticle>
				<titreArticle>L'&#195;&#169;tat de sant&#195;&#169; du prince Rainier &#194;&#171; pr&#195;&#169;occupant &#194;&#187; (25/03/2005)</titreArticle>
			</VOIRAUSSI>
		</LES_VOIRAUSSI>
		<FOCUS>
			<urlArticle>/news/monde/0,,3209553-VU5WX0lEIDUy,00.html</urlArticle>
			<titreArticle>P&#195;&#162;ques : le pape en liaison vid&#195;&#169;o</titreArticle>
			<urlImage>http://s.tf1.fr/mmdia/i/44/8/2021448_2.jpg</urlImage>
			<resumeArticle>Reclu dans ses appartements du Vatican par la maladie, Jean-Paul II a d&#195;&#187; se contenter vendredi soir d'une liaison vid&#195;&#169;o pour marquer sa participation au chemin de croix. Il a exprim&#195;&#169; sa proximit&#195;&#169; "avec tous ceux qui souffrent".</resumeArticle>
			<mailto></mailto>
		</FOCUS>
		<LES_GROSTITRES>
			<GROSTITRE>
				<urlArticle>/news/monde/0,,3209751-VU5WX0lEIDUy,00.html</urlArticle>
				<themeArticle>Diplomatie</themeArticle>
				<titreArticle>Chirac au Japon</titreArticle>
				<urlImage>http://s.tf1.fr/mmdia/i/45/0/2021450_2.jpg</urlImage>
				<resumeArticle>Le chef de l'Etat est arriv&#195;&#169; samedi matin au Japon pour une visite officielle de trois jours ax&#195;&#169;e sur les technologies d'avenir. Devant les industriels, il a lanc&#195;&#169; un appel pour renforcer les liens entre les deux pays.</resumeArticle>
			</GROSTITRE>
			<GROSTITRE>
				<urlArticle>/news/monde/0,,3209555-VU5WX0lEIDUy,00.html</urlArticle>
				<themeArticle>Kirghizstan</themeArticle>
				<titreArticle>Un nouveau pr&#195;&#169;sident</titreArticle>
				<urlImage>http://s.tf1.fr/mmdia/i/38/5/2021385_2.jpg</urlImage>
				<resumeArticle>Le Parlement kirghiz a d&#195;&#169;sign&#195;&#169; vendredi l'un des principaux leaders de l'opposition, Kourmanbek Bakiev, pr&#195;&#169;sident et &#194;&#160;Premier ministre par int&#195;&#169;rim du Kirghizstan.</resumeArticle>
			</GROSTITRE>
			<GROSTITRE>
				<urlArticle>/news/monde/0,,3209458-VU5WX0lEIDUy,00.html</urlArticle>
				<themeArticle>Br&#195;&#169;sil</themeArticle>
				<titreArticle>Les familles des footballeurs menac&#195;&#169;es</titreArticle>
				<urlImage>http://s.tf1.fr/mmdia/i/48/9/28489_2.jpg</urlImage>
				<resumeArticle>L'enl&#195;&#168;vement ces derniers mois des m&#195;&#168;res de quatre footballeurs br&#195;&#169;siliens a cr&#195;&#169;&#195;&#169; une psychose au sein de la Sele&#195;&#167;ao (s&#195;&#169;lection nationale). Plusieurs internationaux ont d&#195;&#169;cid&#195;&#169; de rapatrier leur famille en Europe ou d'embaucher des gardes du corps.</resumeArticle>
			</GROSTITRE>
			<GROSTITRE>
				<urlArticle>/news/monde/0,,3209554-VU5WX0lEIDUy,00.html</urlArticle>
				<themeArticle>Soudan</themeArticle>
				<titreArticle>L'Onu envoie 10 000 casques bleus</titreArticle>
				<urlImage>http://s.tf1.fr/mmdia/i/46/1/1056461_2.jpg</urlImage>
				<resumeArticle>Le Conseil de s&#195;&#169;curit&#195;&#169; de l'Onu a d&#195;&#169;cid&#195;&#169; d'envoyer une mission de 10.000 hommes au Soudan pour soutenir un accord de paix sign&#195;&#169; en janvier ayant mis fin &#195;&#160; une guerre civile de 21 ans.</resumeArticle>
			</GROSTITRE>
			<GROSTITRE>
				<urlArticle>/news/monde/0,,3209468-VU5WX0lEIDUy,00.html</urlArticle>
				<themeArticle>Etats-Unis</themeArticle>
				<titreArticle>Terri Schiavo ne sera pas rebranch&#195;&#169;e</titreArticle>
				<urlImage>http://s.tf1.fr/mmdia/i/41/1/2021411_2.jpg</urlImage>
				<resumeArticle>Apr&#195;&#168;s le rejet de deux nouveaux recours, par la Cour supr&#195;&#170;me et par une juridiction locale de Tampa, le cath&#195;&#169;ter d'alimentation de Terri Schiavo, cette Am&#195;&#169;ricaine se trouvant dans un &#195;&#169;tat v&#195;&#169;g&#195;&#169;tatif depuis 15 ans, ne sera pas remis en fonction. Il lui reste donc seulement quelques jours &#195;&#160; vivre.</resumeArticle>
			</GROSTITRE>
			<GROSTITRE>
				<urlArticle>/news/monde/0,,3209665-VU5WX0lEIDUy,00.html</urlArticle>
				<themeArticle>Diplomatie</themeArticle>
				<titreArticle>Chirac renoue avec le Japon</titreArticle>
				<urlImage>http://s.tf1.fr/mmdia/i/52/0/609520_2.jpg</urlImage>
				<resumeArticle>Le chef de l'Etat retourne au Japon, pays qu'il affectionne, pour la premi&#195;&#168;re fois depuis 5 ans. Partenariats dans les nouvelles technologies et dans le domaine industriel seront au menu des discussions. Ombres au tableau : la lev&#195;&#169;e de l'embargo europ&#195;&#169;en sur les vente d'armes &#195;&#160; la Chine et le choix du site de construction du r&#195;&#169;acteur Iter.</resumeArticle>
			</GROSTITRE>
		</LES_GROSTITRES>
		<LES_RAPPELS>
			<RAPPEL>
				<dateArticle>24 mars</dateArticle>
				<themeArticle>Kirghizstan</themeArticle>
				<titreArticle>R&#195;&#169;volution express</titreArticle>
				<urlArticle>/news/monde/0,,3209373-VU5WX0lEIDUy,00.html</urlArticle>
			</RAPPEL>
			<RAPPEL>
				<dateArticle>24 mars</dateArticle>
				<themeArticle>Etats-Unis</themeArticle>
				<titreArticle>14 morts dans l'explosion d'une raffinerie</titreArticle>
				<urlArticle>/news/monde/0,,3209361-VU5WX0lEIDUy,00.html</urlArticle>
			</RAPPEL>
			<RAPPEL>
				<dateArticle>23 mars</dateArticle>
				<themeArticle>UE</themeArticle>
				<titreArticle>Chirac obtient la refonte de "Bolkestein"</titreArticle>
				<urlArticle>/news/monde/0,,3209171-VU5WX0lEIDUy,00.html</urlArticle>
			</RAPPEL>
			<RAPPEL>
				<dateArticle>23 mars</dateArticle>
				<themeArticle>Liban</themeArticle>
				<titreArticle>Attentat meurtrier pr&#195;&#168;s de Beyrouth</titreArticle>
				<urlArticle>/news/monde/0,,3209155-VU5WX0lEIDUy,00.html</urlArticle>
			</RAPPEL>
			<RAPPEL>
				<dateArticle>23 mars</dateArticle>
				<themeArticle>Charles et Camilla</themeArticle>
				<titreArticle>Deux fils pour t&#195;&#169;moins</titreArticle>
				<urlArticle>/news/monde/0,,3209262-VU5WX0lEIDUy,00.html</urlArticle>
			</RAPPEL>
			<RAPPEL>
				<dateArticle>22 mars</dateArticle>
				<themeArticle>Etats-Unis</themeArticle>
				<titreArticle>Le forcen&#195;&#169; &#195;&#169;tait fascin&#195;&#169; par le nazisme</titreArticle>
				<urlArticle>/news/monde/0,,3208923-VU5WX0lEIDUy,00.html</urlArticle>
			</RAPPEL>
		</LES_RAPPELS>
	</PAGE_LCI>
