	<PAGE_LCI>
		<FICHIER>lci-monde-2005-12-20.html</FICHIER>
		<DATE_PAGE>20/12/2005</DATE_PAGE>
		<UNE>
			<urlArticle>/news/monde/0,,3274047-VU5WX0lEIDUy,00.html</urlArticle>
			<titreArticle>Netanyahu prend la t&#195;&#170;te du Likoud</titreArticle>
			<dateArticle>20/12/2005</dateArticle>
			<urlImage>http://s.tf1.fr/mmdia/i/20/4/609204.gif</urlImage>
			<resumeArticle> Sans surprise, l'ex-Premier ministre isra&#195;&#169;lien a &#195;&#169;t&#195;&#169; &#195;&#169;lu lundi &#195;&#160; la t&#195;&#170;te du parti de droite. C'est donc lui qui m&#195;&#168;nera la formation aux l&#195;&#169;gislatives du 28 mars. Les sondages donnent pour l'instant l'avantage &#195;&#160; "Kadima", le nouveau parti d'Ariel Sharon.</resumeArticle>
			<mailto></mailto>
		</UNE>
		<LES_VOIRAUSSI>
			<VOIRAUSSI>
				<dateArticle>18/12/2005</dateArticle>
				<urlArticle>/news/monde/0,,3273714-VU5WX0lEIDUy,00.html</urlArticle>
				<titreArticle>Sharon victime d'une attaque c&#195;&#169;r&#195;&#169;brale (18/12/2005)</titreArticle>
			</VOIRAUSSI>
			<VOIRAUSSI>
				<dateArticle>19/12/2005</dateArticle>
				<urlArticle>/news/monde/0,,3273767-VU5WX0lEIDUy,00.html</urlArticle>
				<titreArticle>Sharon : "Je suis encore l&#195;&#160;" (19/12/2005)</titreArticle>
			</VOIRAUSSI>
			<VOIRAUSSI>
				<dateArticle>19/12/2005</dateArticle>
				<urlArticle>/news/monde/0,,3273930-VU5WX0lEIDUy,00.html</urlArticle>
				<titreArticle>Netanyahu &#195;&#160; la t&#195;&#170;te du Likoud ? (19/12/2005)</titreArticle>
			</VOIRAUSSI>
		</LES_VOIRAUSSI>
		<FOCUS>
			<urlArticle>/news/monde/0,,3272904-VU5WX0lEIDUy,00.html</urlArticle>
			<titreArticle>Appel &#195;&#160; t&#195;&#169;moins : le tsunami, un an apr&#195;&#168;s</titreArticle>
			<urlImage>http://s.tf1.fr/mmdia/i/60/2/2012602_2.jpg</urlImage>
			<resumeArticle>Un an apr&#195;&#168;s le raz-de-mar&#195;&#169;e du 26 d&#195;&#169;cembre, vous allez vous rendre prochainement dans les r&#195;&#169;gions frapp&#195;&#169;es par la catastrophe ? Envoyez vos photos ou vos vid&#195;&#169;os &#195;&#160; tf1.fr pour t&#195;&#169;moigner sur l'&#195;&#169;tat de la reconstruction.</resumeArticle>
			<mailto></mailto>
		</FOCUS>
		<LES_GROSTITRES>
			<GROSTITRE>
				<urlArticle>/news/monde/0,,3274086-VU5WX0lEIDUy,00.html</urlArticle>
				<themeArticle>Isra&#195;&#171;l</themeArticle>
				<titreArticle>Sharon sort de l'h&#195;&#180;pital</titreArticle>
				<urlImage>http://s.tf1.fr/mmdia/i/62/6/2159626_2.jpg</urlImage>
				<resumeArticle>Victime dimanche d'une "l&#195;&#169;g&#195;&#168;re attaque c&#195;&#169;r&#195;&#169;brale", le Premier ministre isra&#195;&#169;lien a quitt&#195;&#169; mardi matin l'&#195;&#169;tablissement o&#195;&#185; il &#195;&#169;tait hospitalis&#195;&#169;.</resumeArticle>
			</GROSTITRE>
			<GROSTITRE>
				<urlArticle>/news/monde/0,,3274051-VU5WX0lEIDUy,00.html</urlArticle>
				<themeArticle>Justice</themeArticle>
				<titreArticle>Charlotte et sa m&#195;&#168;re se sont vues</titreArticle>
				<urlImage>http://s.tf1.fr/mmdia/i/68/4/2046684_2.jpg</urlImage>
				<resumeArticle>Pour la premi&#195;&#168;re fois depuis un an, Sophie Maumousseau, la Fran&#195;&#167;aise qui se dispute avec son ex-mari am&#195;&#169;ricain la garde de leur fille, a pu rencontrer Charlotte lundi soir aux Etats-Unis.</resumeArticle>
			</GROSTITRE>
			<GROSTITRE>
				<urlArticle>/news/monde/0,,3273771-VU5WX0lEIDUy,00.html</urlArticle>
				<themeArticle>Irak</themeArticle>
				<titreArticle>"Nous sommes en train de gagner la guerre"</titreArticle>
				<urlImage>http://s.tf1.fr/mmdia/i/42/1/2159421_2.jpg</urlImage>
				<resumeArticle>Le pr&#195;&#169;sident am&#195;&#169;ricain a rejet&#195;&#169; dimanche tout "d&#195;&#169;faitisme" pour l'Irak, assurant que les Etats-Unis &#195;&#169;taient "en train de gagner la guerre" m&#195;&#170;me si des "sacrifices" attendent encore les Am&#195;&#169;ricains.</resumeArticle>
			</GROSTITRE>
			<GROSTITRE>
				<urlArticle>/news/monde/0,,3273886-VU5WX0lEIDUy,00.html</urlArticle>
				<themeArticle>Banlieues</themeArticle>
				<titreArticle>Le pape appelle la France &#195;&#160; relever le d&#195;&#169;fi</titreArticle>
				<urlImage>http://s.tf1.fr/mmdia/i/36/2/2047362_2.jpg</urlImage>
				<resumeArticle>Beno&#195;&#174;t XVI a &#195;&#169;voqu&#195;&#169; lundi les r&#195;&#169;centes &#195;&#169;meutes dans les banlieues fran&#195;&#167;aises. Il estime que ces violences "que l'on ne peut que condamner, constituent cependant un message" qu'il faut "prendre en consid&#195;&#169;ration".</resumeArticle>
			</GROSTITRE>
			<GROSTITRE>
				<urlArticle>/news/monde/0,,3273791-VU5WX0lEIDUy,00.html</urlArticle>
				<themeArticle>Royaume-Uni</themeArticle>
				<titreArticle>Elles se sont dit oui !</titreArticle>
				<urlImage>http://s.tf1.fr/mmdia/i/44/6/2159446_2.jpg</urlImage>
				<resumeArticle>Deux femmes ont scell&#195;&#169; lundi en Irlande du Nord, la premi&#195;&#168;re union homosexuelle de l'histoire du Royaume-Uni. La nouvelle loi autorise un partenariat civil qui donne aux conjoints d'un m&#195;&#170;me sexe les m&#195;&#170;mes droits l&#195;&#169;gaux qu'un couple mari&#195;&#169;.</resumeArticle>
			</GROSTITRE>
			<GROSTITRE>
				<urlArticle>/news/monde/0,,3273931-VU5WX0lEIDUy,00.html</urlArticle>
				<themeArticle>Terrorisme</themeArticle>
				<titreArticle>Bush poursuivra les &#195;&#169;coutes</titreArticle>
				<urlImage>http://s.tf1.fr/mmdia/i/56/8/2159568_2.jpg</urlImage>
				<resumeArticle>Le pr&#195;&#169;sident am&#195;&#169;ricain a r&#195;&#169;affirm&#195;&#169; lundi qu'il continuera &#195;&#160; autoriser les &#195;&#169;coutes aussi longtemps que les Am&#195;&#169;ricains seront confront&#195;&#169;s &#195;&#160; la menace terroriste.</resumeArticle>
			</GROSTITRE>
			<GROSTITRE>
				<urlArticle>/news/monde/0,,3273770-VU5WX0lEIDUy,00.html</urlArticle>
				<themeArticle>Bolivie</themeArticle>
				<titreArticle>Un Indien &#195;&#160; la pr&#195;&#169;sidence</titreArticle>
				<urlImage>http://s.tf1.fr/mmdia/i/42/2/2159422_2.jpg</urlImage>
				<resumeArticle>Le premier pr&#195;&#169;sident am&#195;&#169;rindien du pays, un socialiste, a promis de faire payer aux multinationales les exploitations gazi&#195;&#168;res et de d&#195;&#169;fendre les planteurs de coca.</resumeArticle>
			</GROSTITRE>
		</LES_GROSTITRES>
		<LES_RAPPELS>
			<RAPPEL>
				<dateArticle>19 d&#195;&#169;cembre</dateArticle>
				<themeArticle>Irak</themeArticle>
				<titreArticle>L'otage allemande et son chauffeur lib&#195;&#169;r&#195;&#169;s</titreArticle>
				<urlArticle>/news/monde/0,,3273713-VU5WX0lEIDUy,00.html</urlArticle>
			</RAPPEL>
			<RAPPEL>
				<dateArticle>18 d&#195;&#169;cembre</dateArticle>
				<themeArticle>Avions ant&#195;&#180;mes</themeArticle>
				<titreArticle>"Les Europ&#195;&#169;ens savaient"</titreArticle>
				<urlArticle>/news/monde/0,,3273706-VU5WX0lEIDUy,00.html</urlArticle>
			</RAPPEL>
			<RAPPEL>
				<dateArticle>18 d&#195;&#169;cembre</dateArticle>
				<themeArticle>Proche-Orient</themeArticle>
				<titreArticle>Sharon victime d'une attaque c&#195;&#169;r&#195;&#169;brale</titreArticle>
				<urlArticle>/news/monde/0,,3273714-VU5WX0lEIDUy,00.html</urlArticle>
			</RAPPEL>
			<RAPPEL>
				<dateArticle>18 d&#195;&#169;cembre</dateArticle>
				<themeArticle>Aghanistan</themeArticle>
				<titreArticle>Des soldats fran&#195;&#167;ais en renfort</titreArticle>
				<urlArticle>/news/monde/0,,3273707-VU5WX0lEIDUy,00.html</urlArticle>
			</RAPPEL>
			<RAPPEL>
				<dateArticle>18 d&#195;&#169;cembre</dateArticle>
				<themeArticle>RDC</themeArticle>
				<titreArticle>Les Congolais se prononcent sur la Constitution</titreArticle>
				<urlArticle>/news/monde/0,,3273620-VU5WX0lEIDUy,00.html</urlArticle>
			</RAPPEL>
			<RAPPEL>
				<dateArticle>17 d&#195;&#169;cembre</dateArticle>
				<themeArticle>Alg&#195;&#169;rie</themeArticle>
				<titreArticle>Bouteflika quitte l'h&#195;&#180;pital mais reste &#195;&#160; Paris</titreArticle>
				<urlArticle>/news/monde/0,,3273438-VU5WX0lEIDUy,00.html</urlArticle>
			</RAPPEL>
			<RAPPEL>
				<dateArticle>17 d&#195;&#169;cembre</dateArticle>
				<themeArticle>Terrorisme</themeArticle>
				<titreArticle>Bush reconna&#195;&#174;t des &#195;&#169;coutes</titreArticle>
				<urlArticle>/news/monde/0,,3273494-VU5WX0lEIDUy,00.html</urlArticle>
			</RAPPEL>
			<RAPPEL>
				<dateArticle>17 d&#195;&#169;cembre</dateArticle>
				<themeArticle>UE</themeArticle>
				<titreArticle>Accord &#195;&#160; l'arrach&#195;&#169; sur le budget</titreArticle>
				<urlArticle>/news/monde/0,,3273424-VU5WX0lEIDUy,00.html</urlArticle>
			</RAPPEL>
			<RAPPEL>
				<dateArticle>17 d&#195;&#169;cembre</dateArticle>
				<themeArticle>Attentats de Londres</themeArticle>
				<titreArticle>Ils n'&#195;&#169;taient pas jug&#195;&#169;s mena&#195;&#167;ants</titreArticle>
				<urlArticle>/news/monde/0,,3273427-VU5WX0lEIDUy,00.html</urlArticle>
			</RAPPEL>
			<RAPPEL>
				<dateArticle>16 d&#195;&#169;cembre</dateArticle>
				<themeArticle>Irak</themeArticle>
				<titreArticle>Forte participation aux l&#195;&#169;gislatives</titreArticle>
				<urlArticle>/news/monde/0,,3273380-VU5WX0lEIDUy,00.html</urlArticle>
			</RAPPEL>
		</LES_RAPPELS>
	</PAGE_LCI>
