	<PAGE_LCI>
		<FICHIER>lci-monde-2005-10-21.html</FICHIER>
		<DATE_PAGE>21/10/2005</DATE_PAGE>
		<UNE>
			<urlArticle>/news/monde/0,,3256174-VU5WX0lEIDUy,00.html</urlArticle>
			<titreArticle>Un avocat du proc&#195;&#168;s Saddam assassin&#195;&#169;</titreArticle>
			<dateArticle>21/10/2005</dateArticle>
			<urlImage>http://s.tf1.fr/mmdia/i/20/4/609204.gif</urlImage>
			<resumeArticle> L'avocat d'un des co-accus&#195;&#169;s de Saddam Hussein, Me Saadoun Janabi, enlev&#195;&#169; jeudi soir, a &#195;&#169;t&#195;&#169; tu&#195;&#169; par ses ravisseurs. Son corps a &#195;&#169;t&#195;&#169; retrouv&#195;&#169; dans le nord-est de Bagdad.</resumeArticle>
			<mailto>aguillet@tf1.fr</mailto>
		</UNE>
		<LES_VOIRAUSSI>
			<VOIRAUSSI>
				<dateArticle>18/10/2005</dateArticle>
				<urlArticle>/news</urlArticle>
				<titreArticle>"Veulent-ils juger Saddam &#195;&#160; la Ceaucescu ?" (18/10/2005)</titreArticle>
			</VOIRAUSSI>
			<VOIRAUSSI>
				<dateArticle>19/10/2005</dateArticle>
				<urlArticle>/news</urlArticle>
				<titreArticle>"Le TSI est l&#195;&#169;gal, mais on peut &#195;&#170;tre inquiet pour la d&#195;&#169;fense de Saddam" (19/10/2005)</titreArticle>
			</VOIRAUSSI>
			<VOIRAUSSI>
				<dateArticle>19/10/2005</dateArticle>
				<urlArticle>/news</urlArticle>
				<titreArticle>Le proc&#195;&#168;s de Saddam ajourn&#195;&#169; (19/10/2005)</titreArticle>
			</VOIRAUSSI>
			<VOIRAUSSI>
				<dateArticle>20/10/2005</dateArticle>
				<urlArticle>/news</urlArticle>
				<titreArticle>Irak : le journaliste du Guardian lib&#195;&#169;r&#195;&#169; (20/10/2005)</titreArticle>
			</VOIRAUSSI>
		</LES_VOIRAUSSI>
		<FOCUS>
			<urlArticle>/news/monde/0,,3256021-VU5WX0lEIDUy,00.html</urlArticle>
			<titreArticle>"Les Fran&#195;&#167;ais doivent donner pour le Pakistan"</titreArticle>
			<urlImage>http://s.tf1.fr/mmdia/i/37/3/2136373_2.jpg</urlImage>
			<resumeArticle>R&#195;&#169;agissant aux propos de l'ONU qui parle de son "pire cauchemar humanitaire", Thomas Gonnet, le directeur des op&#195;&#169;rations d'Action contre la faim, confirme &#195;&#160; tf1.fr que les &#195;&#169;quipes de l'ONG sont confront&#195;&#169;es &#195;&#160; une situation catastrophique au Pakistan. Et il lance surtout un appel &#195;&#160; la g&#195;&#169;n&#195;&#169;rosit&#195;&#169;.</resumeArticle>
			<mailto>faubert@tf1.fr</mailto>
		</FOCUS>
		<LES_GROSTITRES>
			<GROSTITRE>
				<urlArticle>/news/monde/0,,3256118-VU5WX0lEIDUy,00.html</urlArticle>
				<themeArticle>Wilma</themeArticle>
				<titreArticle>Le Mexique se pr&#195;&#169;pare</titreArticle>
				<urlImage>http://s.tf1.fr/mmdia/i/42/8/2136428_2.jpg</urlImage>
				<resumeArticle>Le cyclone, consid&#195;&#169;r&#195;&#169; comme "extr&#195;&#170;mement dangereux", doit toucher ce matin les c&#195;&#169;l&#195;&#168;bres plages de Cancun. Des milliers de touristes ont &#195;&#169;t&#195;&#169; &#195;&#169;vacu&#195;&#169;s. Cuba et la Floride, o&#195;&#185; l'&#195;&#169;tat d'urgence a &#195;&#169;t&#195;&#169; d&#195;&#169;cr&#195;&#169;t&#195;&#169;, se pr&#195;&#169;parent &#195;&#160; leur tour.</resumeArticle>
			</GROSTITRE>
			<GROSTITRE>
				<urlArticle>/news/monde/0,,3256163-VU5WX0lEIDUy,00.html</urlArticle>
				<themeArticle>Etats-Unis</themeArticle>
				<titreArticle>"Schwarzy" boude Bush</titreArticle>
				<urlImage>http://s.tf1.fr/mmdia/i/42/5/2001425_2.jpg</urlImage>
				<resumeArticle>Le gouverneur Arnold Schwarzenegger, en pleine campagne r&#195;&#169;f&#195;&#169;rendaire, n'appr&#195;&#169;cie pas la visite californienne du pr&#195;&#169;sident, venu collecter des fonds pour le parti r&#195;&#169;publicain.</resumeArticle>
			</GROSTITRE>
			<GROSTITRE>
				<urlArticle>/news/monde/0,,3256119-VU5WX0lEIDUy,00.html</urlArticle>
				<themeArticle>Rapport Hariri</themeArticle>
				<titreArticle>La Syrie et le Liban impliqu&#195;&#169;s</titreArticle>
				<urlImage>http://s.tf1.fr/mmdia/i/43/1/2136431_2.jpg</urlImage>
				<resumeArticle>Des responsables&#194;&#160;syriens de haut rang et leurs alli&#195;&#169;s libanais sont impliqu&#195;&#169;s dans&#194;&#160;l'assassinat de l'ancien Premier ministre libanais,&#194;&#160;estime le rapport d'enqu&#195;&#170;te de l'Onu.</resumeArticle>
			</GROSTITRE>
			<GROSTITRE>
				<urlArticle>/news/monde/0,,3256095-VU5WX0lEIDUy,00.html</urlArticle>
				<themeArticle>Irak</themeArticle>
				<titreArticle>Le journaliste du Guardian lib&#195;&#169;r&#195;&#169;</titreArticle>
				<urlImage>http://s.tf1.fr/mmdia/i/45/8/2136458_2.jpg</urlImage>
				<resumeArticle>Le journaliste irlandais du Guardian, enlev&#195;&#169; mercredi en Irak, a &#195;&#169;t&#195;&#169; lib&#195;&#169;r&#195;&#169; "sain et sauf" jeudi soir.</resumeArticle>
			</GROSTITRE>
			<GROSTITRE>
				<urlArticle>/news/monde/0,,3256035-VU5WX0lEIDUy,00.html</urlArticle>
				<themeArticle>Unesco</themeArticle>
				<titreArticle>La diversit&#195;&#169; culturelle reconnue</titreArticle>
				<urlImage>http://s.tf1.fr/mmdia/i/39/0/2136390_2.jpg</urlImage>
				<resumeArticle>Les repr&#195;&#169;sentants de l'UNESCO ont adopt&#195;&#169; massivement jeudi la convention sur la diversit&#195;&#169; culturelle au terme d'un vif d&#195;&#169;bat qui a laiss&#195;&#169; les Etats-Unis, oppos&#195;&#169;s au texte, isol&#195;&#169;s.</resumeArticle>
			</GROSTITRE>
			<GROSTITRE>
				<urlArticle>/news/monde/0,,3256004-VU5WX0lEIDUy,00.html</urlArticle>
				<themeArticle>Pakistan</themeArticle>
				<titreArticle>"Le pire cauchemar de l'ONU"</titreArticle>
				<urlImage>http://s.tf1.fr/mmdia/i/35/8/2136358_2.jpg</urlImage>
				<resumeArticle>Les Nations unies mettent en garde la communaut&#195;&#169; internationale contre une catastrophe humanitaire &#195;&#160; venir au Pakistan cet hiver si les dons ne d&#195;&#169;collent pas.</resumeArticle>
			</GROSTITRE>
			<GROSTITRE>
				<urlArticle>/news/monde/0,,3255884-VU5WX0lEIDUy,00.html</urlArticle>
				<themeArticle>Iran</themeArticle>
				<titreArticle>Haro sur les films la&#195;&#175;ques et f&#195;&#169;ministes</titreArticle>
				<urlImage>http://s.tf1.fr/mmdia/i/24/6/824246_2.jpg</urlImage>
				<resumeArticle>Les films &#195;&#169;trangers pr&#195;&#180;nant notamment des id&#195;&#169;es la&#195;&#175;ques et f&#195;&#169;ministes sont d&#195;&#169;sormais interdits &#195;&#160; la t&#195;&#169;l&#195;&#169;vision iranienne. La d&#195;&#169;cision a &#195;&#169;t&#195;&#169; prise par le Conseil supr&#195;&#170;me de la r&#195;&#169;volution culturelle, dirig&#195;&#169; par le nouveau pr&#195;&#169;sident ultraconservateur Mahmoud Ahmadinejad.</resumeArticle>
			</GROSTITRE>
			<GROSTITRE>
				<urlArticle>/news/monde/0,,3255824-VU5WX0lEIDUy,00.html</urlArticle>
				<themeArticle>Wilma</themeArticle>
				<titreArticle>A son approche, les a&#195;&#169;roports font le plein</titreArticle>
				<urlImage>http://s.tf1.fr/mmdia/i/22/0/2136220_2.jpg</urlImage>
				<resumeArticle>Le cyclone, qui a l&#195;&#169;g&#195;&#168;rement faibli mais reste "tr&#195;&#168;s dangereux", progressait ce matin vers l'est du Mexique et Cuba, o&#195;&#185; les populations menac&#195;&#169;es sont en cours d'&#195;&#169;vacuation. Wilma devrait ensuite traverser la pointe sud de la Floride &#195;&#160; la fin de la semaine.</resumeArticle>
			</GROSTITRE>
		</LES_GROSTITRES>
		<LES_RAPPELS>
			<RAPPEL>
				<dateArticle>19 octobre</dateArticle>
				<themeArticle>Irak</themeArticle>
				<titreArticle>Le proc&#195;&#168;s de Saddam ajourn&#195;&#169;</titreArticle>
				<urlArticle>/news/monde/0,,3255541-VU5WX0lEIDUy,00.html</urlArticle>
			</RAPPEL>
			<RAPPEL>
				<dateArticle>19 octobre</dateArticle>
				<themeArticle>Irak</themeArticle>
				<titreArticle>"Le TSI est l&#195;&#169;gal, mais on peut &#195;&#170;tre inquiet pour la d&#195;&#169;fense de Saddam"</titreArticle>
				<urlArticle>/news/monde/0,,3255230-VU5WX0lEIDUy,00.html</urlArticle>
			</RAPPEL>
			<RAPPEL>
				<dateArticle>19 octobre</dateArticle>
				<themeArticle>Irak</themeArticle>
				<titreArticle>La valse des avocats de Saddam</titreArticle>
				<urlArticle>/news/monde/0,,3255374-VU5WX0lEIDUy,00.html</urlArticle>
			</RAPPEL>
			<RAPPEL>
				<dateArticle>18 octobre</dateArticle>
				<themeArticle>Irak</themeArticle>
				<titreArticle>"Veulent-ils juger Saddam &#195;&#160; la Ceaucescu ?"</titreArticle>
				<urlArticle>/news/monde/0,,3254995-VU5WX0lEIDUy,00.html</urlArticle>
			</RAPPEL>
			<RAPPEL>
				<dateArticle>19 octobre</dateArticle>
				<themeArticle>Pakistan</themeArticle>
				<titreArticle>Fortes r&#195;&#169;pliques sismiques dans le nord</titreArticle>
				<urlArticle>/news/monde/0,,3255473-VU5WX0lEIDUy,00.html</urlArticle>
			</RAPPEL>
			<RAPPEL>
				<dateArticle>18 octobre</dateArticle>
				<themeArticle>Ouragan</themeArticle>
				<titreArticle>Wilma "potentiellement catastrophique"</titreArticle>
				<urlArticle>/news/monde/0,,3255225-VU5WX0lEIDUy,00.html</urlArticle>
			</RAPPEL>
			<RAPPEL>
				<dateArticle>18 octobre</dateArticle>
				<themeArticle>Irak </themeArticle>
				<titreArticle>L'annonce des r&#195;&#169;sultats du r&#195;&#169;f&#195;&#169;rendum report&#195;&#169;e</titreArticle>
				<urlArticle>/news/monde/0,,3255168-VU5WX0lEIDUy,00.html</urlArticle>
			</RAPPEL>
			<RAPPEL>
				<dateArticle>17 octobre</dateArticle>
				<themeArticle>Pakistan</themeArticle>
				<titreArticle>Plus de 54.000 morts dans le s&#195;&#169;isme</titreArticle>
				<urlArticle>/news/monde/0,,3254404-VU5WX0lEIDUy,00.html</urlArticle>
			</RAPPEL>
		</LES_RAPPELS>
	</PAGE_LCI>
