	<PAGE_LCI>
		<FICHIER>lci-monde-2005-12-15.html</FICHIER>
		<DATE_PAGE>15/12/2005</DATE_PAGE>
		<UNE>
			<urlArticle>/news/monde/0,,3272689-VU5WX0lEIDUy,00.html</urlArticle>
			<titreArticle>Irak : retour aux urnes dans la peur</titreArticle>
			<dateArticle>15/12/2005</dateArticle>
			<urlImage>http://s.tf1.fr/mmdia/i/20/4/609204.gif</urlImage>
			<resumeArticle> Apr&#195;&#168;s l'Assembl&#195;&#169;e constituante en janvier et le r&#195;&#169;f&#195;&#169;rendum qui en a d&#195;&#169;coul&#195;&#169; en octobre, les Irakiens &#195;&#169;lisent aujourd'hui les 275 d&#195;&#169;put&#195;&#169;s de l'Assembl&#195;&#169;e nationale d&#195;&#169;finitive. Une nouvelle fois, le vote s'effectue dans la peur d'attentats de la gu&#195;&#169;rilla men&#195;&#169;e par Zarqaoui.</resumeArticle>
			<mailto>faubert@tf1.fr</mailto>
		</UNE>
		<LES_VOIRAUSSI>
			<VOIRAUSSI>
				<dateArticle>16/03/2005</dateArticle>
				<urlArticle>/news/monde/0,,3207914-VU5WX0lEIDUy,00.html</urlArticle>
				<titreArticle>Jour historique pour l'Assembl&#195;&#169;e irakienne (16/03/2005)</titreArticle>
			</VOIRAUSSI>
			<VOIRAUSSI>
				<dateArticle>06/04/2005</dateArticle>
				<urlArticle>/news/monde/0,,3211705-VU5WX0lEIDUy,00.html</urlArticle>
				<titreArticle>Un Kurde pr&#195;&#169;sident de l'Irak (06/04/2005)</titreArticle>
			</VOIRAUSSI>
			<VOIRAUSSI>
				<dateArticle>15/10/2005</dateArticle>
				<urlArticle>/news/monde/0,,3254233-VU5WX0lEIDUy,00.html</urlArticle>
				<titreArticle>R&#195;&#169;f&#195;&#169;rendum en Irak : plus de 61% de participation (15/10/2005)</titreArticle>
			</VOIRAUSSI>
			<VOIRAUSSI>
				<dateArticle>25/10/2005</dateArticle>
				<urlArticle>/news/monde/0,,3257294-VU5WX0lEIDUy,00.html</urlArticle>
				<titreArticle>Irak : le projet de Constitution ratifi&#195;&#169; (25/10/2005)</titreArticle>
			</VOIRAUSSI>
		</LES_VOIRAUSSI>
		<FOCUS>
			<urlArticle>/news/monde/0,,3272904-VU5WX0lEIDUy,00.html</urlArticle>
			<titreArticle>Appel &#195;&#160; t&#195;&#169;moins : le tsunami, un an apr&#195;&#168;s</titreArticle>
			<urlImage>http://s.tf1.fr/mmdia/i/60/2/2012602_2.jpg</urlImage>
			<resumeArticle>Un an apr&#195;&#168;s le raz-de-mar&#195;&#169;e du 26 d&#195;&#169;cembre, vous allez vous rendre prochainement dans les r&#195;&#169;gions frapp&#195;&#169;es par la catastrophe ? Envoyez vos photos ou vos vid&#195;&#169;os &#195;&#160; tf1.fr pour t&#195;&#169;moigner sur l'&#195;&#169;tat de la reconstruction.</resumeArticle>
			<mailto></mailto>
		</FOCUS>
		<LES_GROSTITRES>
			<GROSTITRE>
				<urlArticle>/news/monde/0,,3272737-VU5WX0lEIDUy,00.html</urlArticle>
				<themeArticle>UE</themeArticle>
				<titreArticle>Blair-Chirac, le budget de tous les dangers</titreArticle>
				<urlImage>http://s.tf1.fr/mmdia/i/43/9/2156439_2.jpg</urlImage>
				<resumeArticle>Les dirigeants europ&#195;&#169;ens se retrouvent &#195;&#160; Bruxelles pour un sommet consacr&#195;&#169; au budget 2007-2013. Comme en juin dernier, l'affrontement entre le Premier ministre britannique, qui d&#195;&#169;fend son "rabais" et le chef de l'Etat, qui soutient la PAC, s'annonce tendu.</resumeArticle>
			</GROSTITRE>
			<GROSTITRE>
				<urlArticle>/news/monde/0,,3272896-VU5WX0lEIDUy,00.html</urlArticle>
				<themeArticle>Etats-Unis</themeArticle>
				<titreArticle>L'imbroglio des passeports biom&#195;&#169;triques</titreArticle>
				<urlImage>http://s.tf1.fr/mmdia/i/74/4/2158744_2.jpg</urlImage>
				<resumeArticle>Depuis le 26 octobre, les Etats-Unis imposent un passeport biom&#195;&#169;trique pour entrer sur leur sol. Mais la France n'ayant pas d&#195;&#169;livr&#195;&#169; ce mod&#195;&#168;le &#195;&#160; temps, les d&#195;&#169;tenteurs des passeports &#195;&#169;mis depuis doivent demander un visa. A contrario, les documents optiques ant&#195;&#169;rieurs au 26 octobre sont toujours valables.</resumeArticle>
			</GROSTITRE>
			<GROSTITRE>
				<urlArticle>/news/monde/0,,3272842-VU5WX0lEIDUy,00.html</urlArticle>
				<themeArticle>Iran</themeArticle>
				<titreArticle>Nouveau toll&#195;&#169; contre Ahmadinejad</titreArticle>
				<urlImage>http://s.tf1.fr/mmdia/i/49/9/2156499_2.jpg</urlImage>
				<resumeArticle>"Inacceptables", "scandaleux" : tels sont les &#195;&#169;pith&#195;&#168;tes qui ont salu&#195;&#169;, de Washington &#195;&#160; J&#195;&#169;rusalem en passant par Paris, Berlin et Madrid, les nouveaux propos de Mahmoud Ahmadinejad sur Isra&#195;&#171;l.</resumeArticle>
			</GROSTITRE>
			<GROSTITRE>
				<urlArticle>/news/monde/0,,3272402-VU5WX0lEIDUy,00.html</urlArticle>
				<themeArticle>Colombie</themeArticle>
				<titreArticle>Un espoir pour Ingrid Betancourt</titreArticle>
				<urlImage>http://s.tf1.fr/mmdia/i/83/3/2042833_2.jpg</urlImage>
				<resumeArticle>Le gouvernement colombien accepte de cr&#195;&#169;er une zone d&#195;&#169;militaris&#195;&#169;e au sud du pays, ouvrant ainsi la voie &#195;&#160; des n&#195;&#169;gociations avec les Forces arm&#195;&#169;es r&#195;&#169;volutionnaires pour la lib&#195;&#169;ration des otages, dont Ingrid Betancourt.</resumeArticle>
			</GROSTITRE>
			<GROSTITRE>
				<urlArticle>/news/monde/0,,3272432-VU5WX0lEIDUy,00.html</urlArticle>
				<themeArticle>Iran</themeArticle>
				<titreArticle>Le pr&#195;&#169;sident nie la Shoah</titreArticle>
				<urlImage>http://s.tf1.fr/mmdia/i/10/6/2138106_2.jpg</urlImage>
				<resumeArticle>Mahmoud Ahmadinejad a lanc&#195;&#169; mercredi soir une nouvelle diatribe contre Isra&#195;&#171;l, en parlant de "mythe" &#195;&#160; propos du "massacre des juifs" par les nazis. Il a repropos&#195;&#169; que l'Etat h&#195;&#169;breu soit cr&#195;&#169;&#195;&#169; "en Europe, aux Etats-Unis, au Canada ou encore en Alaska".</resumeArticle>
			</GROSTITRE>
			<GROSTITRE>
				<urlArticle>/news/monde/0,,3271702-VU5WX0lEIDUy,00.html</urlArticle>
				<themeArticle>Royaume-Uni</themeArticle>
				<titreArticle>L'incendie g&#195;&#169;ant ma&#195;&#174;tris&#195;&#169; &#195;&#160; Buncefield</titreArticle>
				<urlImage>http://s.tf1.fr/mmdia/i/26/1/2158261_2.jpg</urlImage>
				<resumeArticle>Les pompiers britanniques ont ma&#195;&#174;tris&#195;&#169; les incendies des trois derni&#195;&#168;res cuves de p&#195;&#169;trole du d&#195;&#169;p&#195;&#180;t de carburant de Buncefield au nord de Londres. Un &#195;&#169;pais nuage de fum&#195;&#169;e s'&#195;&#169;chappait cependant toujours, mardi soir, du site ravag&#195;&#169;.</resumeArticle>
			</GROSTITRE>
			<GROSTITRE>
				<urlArticle>/news/monde/0,,3272543-VU5WX0lEIDUy,00.html</urlArticle>
				<themeArticle>UE</themeArticle>
				<titreArticle>Blair s'accroche &#195;&#160; son "rabais"</titreArticle>
				<urlImage>http://s.tf1.fr/mmdia/i/81/0/2021810_2.jpg</urlImage>
				<resumeArticle>A la veille du sommet de Bruxelles consacr&#195;&#169; au budget de l'Union europ&#195;&#169;enne, la pr&#195;&#169;sidence britannique fait un -petit- geste en proposant une hausse de l'enveloppe globale de 2 milliards d'euros. Mais pas question de touche au "rabais" dont Londres b&#195;&#169;n&#195;&#169;ficie depuis 1984.</resumeArticle>
			</GROSTITRE>
		</LES_GROSTITRES>
		<LES_RAPPELS>
			<RAPPEL>
				<dateArticle>13 d&#195;&#169;cembre</dateArticle>
				<themeArticle>CIA</themeArticle>
				<titreArticle>Soup&#195;&#167;ons d'enl&#195;&#168;vements en Europe</titreArticle>
				<urlArticle>/news/monde/0,,3272191-VU5WX0lEIDUy,00.html</urlArticle>
			</RAPPEL>
			<RAPPEL>
				<dateArticle>13 d&#195;&#169;cembre</dateArticle>
				<themeArticle>Etats-Unis</themeArticle>
				<titreArticle>"Tookie" a &#195;&#169;t&#195;&#169; ex&#195;&#169;cut&#195;&#169;</titreArticle>
				<urlArticle>/news/monde/0,,3271886-VU5WX0lEIDUy,00.html</urlArticle>
			</RAPPEL>
			<RAPPEL>
				<dateArticle>13 d&#195;&#169;cembre</dateArticle>
				<themeArticle>Pakistan</themeArticle>
				<titreArticle>Une r&#195;&#169;plique sismique provoque la panique</titreArticle>
				<urlArticle>/news/monde/0,,3271878-VU5WX0lEIDUy,00.html</urlArticle>
			</RAPPEL>
			<RAPPEL>
				<dateArticle>12 d&#195;&#169;cembre</dateArticle>
				<themeArticle>Liban</themeArticle>
				<titreArticle>Un d&#195;&#169;put&#195;&#169; antisyrien tu&#195;&#169; dans un attentat</titreArticle>
				<urlArticle>/news/monde/0,,3271254-VU5WX0lEIDUy,00.html</urlArticle>
			</RAPPEL>
			<RAPPEL>
				<dateArticle>12 d&#195;&#169;cembre</dateArticle>
				<themeArticle>Forum</themeArticle>
				<titreArticle>L'Eurom&#195;&#169;diterran&#195;&#169;e et ses d&#195;&#169;fis</titreArticle>
				<urlArticle>/news/monde/0,,3270583-VU5WX0lEIDUy,00.html</urlArticle>
			</RAPPEL>
			<RAPPEL>
				<dateArticle>12 d&#195;&#169;cembre</dateArticle>
				<themeArticle>Chili</themeArticle>
				<titreArticle>La candidate socialiste en t&#195;&#170;te au premier tour</titreArticle>
				<urlArticle>/news/monde/0,,3271250-VU5WX0lEIDUy,00.html</urlArticle>
			</RAPPEL>
			<RAPPEL>
				<dateArticle>11 d&#195;&#169;cembre</dateArticle>
				<themeArticle>Oc&#195;&#169;anie</themeArticle>
				<titreArticle>S&#195;&#169;isme en Papouasie-Nouvelle-Guin&#195;&#169;e</titreArticle>
				<urlArticle>/news/monde/0,,3271168-VU5WX0lEIDUy,00.html</urlArticle>
			</RAPPEL>
			<RAPPEL>
				<dateArticle>11 d&#195;&#169;cembre</dateArticle>
				<themeArticle>Pakistan</themeArticle>
				<titreArticle>Explosion de feux d'artifice, 30 tu&#195;&#169;s</titreArticle>
				<urlArticle>/news/monde/0,,3271183-VU5WX0lEIDUy,00.html</urlArticle>
			</RAPPEL>
			<RAPPEL>
				<dateArticle>10 d&#195;&#169;cembre</dateArticle>
				<themeArticle>Nigeria</themeArticle>
				<titreArticle>105 morts dans un crash d'avion</titreArticle>
				<urlArticle>/news/monde/0,,3270956-VU5WX0lEIDUy,00.html</urlArticle>
			</RAPPEL>
			<RAPPEL>
				<dateArticle>10 d&#195;&#169;cembre</dateArticle>
				<themeArticle>Irak</themeArticle>
				<titreArticle>Fin de l'ultimatum pour quatre otages</titreArticle>
				<urlArticle>/news/monde/0,,3270974-VU5WX0lEIDUy,00.html</urlArticle>
			</RAPPEL>
		</LES_RAPPELS>
	</PAGE_LCI>
