	<PAGE_LCI>
		<FICHIER>lci-monde-2005-11-23.html</FICHIER>
		<DATE_PAGE>23/11/2005</DATE_PAGE>
		<UNE>
			<urlArticle>/news/monde/0,,3265379-VU5WX0lEIDUy,00.html</urlArticle>
			<titreArticle>Merkel-Chirac, premi&#195;&#168;re rencontre</titreArticle>
			<dateArticle>23/11/2005</dateArticle>
			<urlImage>http://s.tf1.fr/mmdia/i/20/4/609204.gif</urlImage>
			<resumeArticle> Entr&#195;&#169;e en fonction hier, la nouvelle Chanceli&#195;&#168;re allemande effectuait aujourd'hui son premier d&#195;&#169;placement &#195;&#160; l'&#195;&#169;tranger Elle a tout d'abord &#195;&#169;t&#195;&#169; accueillie par Jacques Chirac &#195;&#160; l'Elys&#195;&#169;e, avant de se rendre &#195;&#160; Bruxelles au si&#195;&#168;ge de l'Union europ&#195;&#169;enne.</resumeArticle>
			<mailto></mailto>
		</UNE>
		<LES_VOIRAUSSI>
			<VOIRAUSSI>
				<dateArticle>10/10/2005</dateArticle>
				<urlArticle>/news</urlArticle>
				<titreArticle>Merkel prend les r&#195;&#170;nes d'un dr&#195;&#180;le d'attelage (10/10/2005)</titreArticle>
			</VOIRAUSSI>
			<VOIRAUSSI>
				<dateArticle>17/10/2005</dateArticle>
				<urlArticle>/news</urlArticle>
				<titreArticle>Merkel a form&#195;&#169; son &#195;&#169;quipe (17/10/2005)</titreArticle>
			</VOIRAUSSI>
			<VOIRAUSSI>
				<dateArticle>11/11/2005</dateArticle>
				<urlArticle>/news</urlArticle>
				<titreArticle>CDU et SPD s'entendent sur un programme (11/11/2005)</titreArticle>
			</VOIRAUSSI>
			<VOIRAUSSI>
				<dateArticle>14/11/2005</dateArticle>
				<urlArticle>/news</urlArticle>
				<titreArticle>Allemagne : l'accord de coalition ent&#195;&#169;rin&#195;&#169; malgr&#195;&#169; tout (14/11/2005)</titreArticle>
			</VOIRAUSSI>
			<VOIRAUSSI>
				<dateArticle>22/11/2005</dateArticle>
				<urlArticle>/news</urlArticle>
				<titreArticle>Merkel entre &#195;&#160; la Chancellerie (22/11/2005)</titreArticle>
			</VOIRAUSSI>
		</LES_VOIRAUSSI>
		<FOCUS>
			<urlArticle>/news/monde/0,,3265283-VU5WX0lEIDUy,00.html</urlArticle>
			<titreArticle>Sharon bien parti avec son nouveau parti</titreArticle>
			<urlImage>http://s.tf1.fr/mmdia/i/65/0/2046650_2.jpg</urlImage>
			<resumeArticle>Selon les premiers sondages publi&#195;&#169;s apr&#195;&#168;s l'annonce de son d&#195;&#169;part du Likoud pour former sa propre formation centriste, le Premier ministre isra&#195;&#169;lien remporterait les l&#195;&#169;gislatives du printemps. Le Likoud, avec l'hypoth&#195;&#168;se Benjamin Netanyahu, serait loin derri&#195;&#168;re.</resumeArticle>
			<mailto></mailto>
		</FOCUS>
		<LES_GROSTITRES>
			<GROSTITRE>
				<urlArticle>/news/monde/0,,3264775-VU5WX0lEIDUy,00.html</urlArticle>
				<themeArticle>Bosnie</themeArticle>
				<titreArticle>Les accords de Dayton ont dix ans</titreArticle>
				<urlImage>http://s.tf1.fr/mmdia/i/86/8/528868_2.jpg</urlImage>
				<resumeArticle>Il y a dix ans, l'accord de Dayton mettait fin &#195;&#160; trois ans et demi de guerre interethnique en Bosnie. Les dirigeants de ce pays sont &#195;&#160; Washington pour discuter de l'&#195;&#169;volution de ce pays toujours ethniquement divis&#195;&#169;.</resumeArticle>
			</GROSTITRE>
			<GROSTITRE>
				<urlArticle>/news/monde/0,,3264771-VU5WX0lEIDUy,00.html</urlArticle>
				<themeArticle>Isra&#195;&#171;l</themeArticle>
				<titreArticle>Sharon cr&#195;&#169;e un parti pour faire la paix</titreArticle>
				<urlImage>http://s.tf1.fr/mmdia/i/27/3/2145273_2.jpg</urlImage>
				<resumeArticle>Apr&#195;&#168;s avoir d&#195;&#169;missionn&#195;&#169; lundi matin de son poste de premier ministre et du Likoud, Ariel Sharon a annonc&#195;&#169; la cr&#195;&#169;ation de son parti, baptis&#195;&#169; "Responsabilit&#195;&#169; nationale". Le Parlement s'est auto-dissout afin de permettre des &#195;&#169;lections anticip&#195;&#169;es pour le printemps.</resumeArticle>
			</GROSTITRE>
			<GROSTITRE>
				<urlArticle>/news/monde/0,,3264925-VU5WX0lEIDUy,00.html</urlArticle>
				<themeArticle>Allemagne</themeArticle>
				<titreArticle>Merkel entre &#195;&#160; la Chancellerie</titreArticle>
				<urlImage>http://s.tf1.fr/mmdia/i/88/3/2150883_2.jpg</urlImage>
				<resumeArticle>Les d&#195;&#169;put&#195;&#169;s ont officiellement d&#195;&#169;sign&#195;&#169; ce mardi la pr&#195;&#169;sidente de la CDU comme premi&#195;&#168;re chanceli&#195;&#168;re de l'histoire de l'Allemagne. Son gouvernement de "grande coalition" est entr&#195;&#169; en fonctions dans la soir&#195;&#169;e apr&#195;&#168;s la passation de pouvoirs avec Schr&#195;&#182;der.</resumeArticle>
			</GROSTITRE>
			<GROSTITRE>
				<urlArticle>/news/monde/0,,3264597-VU5WX0lEIDUy,00.html</urlArticle>
				<themeArticle>Chine</themeArticle>
				<titreArticle>Bush place des avions, pas les droits de l'homme</titreArticle>
				<urlImage>http://s.tf1.fr/mmdia/i/13/6/2145136_2.jpg</urlImage>
				<resumeArticle>Si son voyage a &#195;&#169;t&#195;&#169; marqu&#195;&#169; par un nouveau contrat pour Boeing, le pr&#195;&#169;sident am&#195;&#169;ricain n'a obtenu aucune concession de son homologue chinois sur les droits de l'homme.</resumeArticle>
			</GROSTITRE>
			<GROSTITRE>
				<urlArticle>/news/monde/0,,3264672-VU5WX0lEIDUy,00.html</urlArticle>
				<themeArticle>Egypte</themeArticle>
				<titreArticle>Coup de filet contre les Fr&#195;&#168;res musulmans</titreArticle>
				<urlImage>http://s.tf1.fr/mmdia/i/34/2/19342_2.jpg</urlImage>
				<resumeArticle>Apr&#195;&#168;s la perc&#195;&#169;e des candidats se r&#195;&#169;clamant de la confr&#195;&#169;rie lors de la premi&#195;&#168;re phase des l&#195;&#169;gislatives, environ 200 Fr&#195;&#168;res musulmans ont &#195;&#169;t&#195;&#169; arr&#195;&#170;t&#195;&#169;s ce week-end en Egypte, au d&#195;&#169;but de la seconde phase.</resumeArticle>
			</GROSTITRE>
			<GROSTITRE>
				<urlArticle>/news/monde/0,,3264697-VU5WX0lEIDUy,00.html</urlArticle>
				<themeArticle>Isra&#195;&#171;l</themeArticle>
				<titreArticle>Les travaillistes quittent le gouvernement Sharon</titreArticle>
				<urlImage>http://s.tf1.fr/mmdia/i/24/0/883240_2.jpg</urlImage>
				<resumeArticle>Le comit&#195;&#169; central du Parti travailliste isra&#195;&#169;lien a d&#195;&#169;cid&#195;&#169; dimanche soir de quitter la coalition du Premier ministre Ariel Sharon. Des &#195;&#169;lections anticip&#195;&#169;es devraient &#195;&#170;tre tenues en f&#195;&#169;vrier-mars.</resumeArticle>
			</GROSTITRE>
		</LES_GROSTITRES>
		<LES_RAPPELS>
			<RAPPEL>
				<dateArticle>19 novembre</dateArticle>
				<themeArticle>Monaco</themeArticle>
				<titreArticle>Le Rocher a intronis&#195;&#169; son prince</titreArticle>
				<urlArticle>/news/monde/0,,3264379-VU5WX0lEIDUy,00.html</urlArticle>
			</RAPPEL>
			<RAPPEL>
				<dateArticle>19 novembre</dateArticle>
				<themeArticle>Pakistan</themeArticle>
				<titreArticle>La communaut&#195;&#169; internationale se mobilise</titreArticle>
				<urlArticle>/news/monde/0,,3264445-VU5WX0lEIDUy,00.html</urlArticle>
			</RAPPEL>
			<RAPPEL>
				<dateArticle>17 novembre</dateArticle>
				<themeArticle>Islamisme</themeArticle>
				<titreArticle>"Le r&#195;&#180;le social d'al-Qa&#195;&#175;da, un investissement sur l'avenir"</titreArticle>
				<urlArticle>/news/monde/0,,3263483-VU5WX0lEIDUy,00.html</urlArticle>
			</RAPPEL>
			<RAPPEL>
				<dateArticle>18 novembre</dateArticle>
				<themeArticle>Irak</themeArticle>
				<titreArticle>Carnage dans 2 mosqu&#195;&#169;es : plus de 70 morts</titreArticle>
				<urlArticle>/news/monde/0,,3264136-VU5WX0lEIDUy,00.html</urlArticle>
			</RAPPEL>
			<RAPPEL>
				<dateArticle>19 novembre</dateArticle>
				<themeArticle>Irak</themeArticle>
				<titreArticle>Au moins 30 morts dans un attentat</titreArticle>
				<urlArticle>/news/monde/0,,3264454-VU5WX0lEIDUy,00.html</urlArticle>
			</RAPPEL>
			<RAPPEL>
				<dateArticle>18 novembre</dateArticle>
				<themeArticle>Terrorisme</themeArticle>
				<titreArticle>Les "avions-fant&#195;&#180;mes" de la CIA sortent de l'ombre</titreArticle>
				<urlArticle>/news/monde/0,,3264228-VU5WX0lEIDUy,00.html</urlArticle>
			</RAPPEL>
			<RAPPEL>
				<dateArticle>18 novembre</dateArticle>
				<themeArticle>Royaume-Uni</themeArticle>
				<titreArticle>Des primes pour les bons &#195;&#169;l&#195;&#168;ves</titreArticle>
				<urlArticle>/news/monde/0,,3264125-VU5WX0lEIDUy,00.html</urlArticle>
			</RAPPEL>
		</LES_RAPPELS>
	</PAGE_LCI>
